{
  "configVersion": 1,
  "index": "/index.html",
  "assetGroups": [
    {
      "name": "app",
      "installMode": "prefetch",
      "updateMode": "prefetch",
      "urls": [
        "/0.552d0c2f87b4951be4b0.js",
        "/1.bbcc166dd123707a4366.js",
        "/2.d168d9579d42cdbd108e.js",
        "/3.82e6d12a823f761f13be.js",
        "/favicon.ico",
        "/index.html",
        "/main.3dee337d6f3c9b1da05b.js",
        "/polyfills.2076bdbe1e0f026d7e99.js",
        "/runtime.a5b6306bd520eff5af97.js",
        "/styles.1f29ab6809b39ca04b10.css"
      ],
      "patterns": []
    },
    {
      "name": "assets",
      "installMode": "lazy",
      "updateMode": "prefetch",
      "urls": [
        "/assets/icons/icon-128x128.png",
        "/assets/icons/icon-144x144.png",
        "/assets/icons/icon-152x152.png",
        "/assets/icons/icon-192x192.png",
        "/assets/icons/icon-384x384.png",
        "/assets/icons/icon-512x512.png",
        "/assets/icons/icon-72x72.png",
        "/assets/icons/icon-96x96.png"
      ],
      "patterns": []
    }
  ],
  "dataGroups": [],
  "hashTable": {
    "/0.552d0c2f87b4951be4b0.js": "9b74940bc0301f9d7647f00bcd5c1b073fbd809c",
    "/1.bbcc166dd123707a4366.js": "b0386b3aa34fd41011074ae08119871e4e483472",
    "/2.d168d9579d42cdbd108e.js": "5957bb8d00b8e6d2a0783d0c1ee33212ccf5bfc3",
    "/3.82e6d12a823f761f13be.js": "057c5aeb7c5674af8278153a9555920beafa1e15",
    "/assets/icons/icon-128x128.png": "cfdecd14e5b436106a19a1e6656661a0cdd22299",
    "/assets/icons/icon-144x144.png": "c2c87e553494cbb0226bdc643f8037d9e151da01",
    "/assets/icons/icon-152x152.png": "121d4853c1e70df065db659065f0c245d63f409d",
    "/assets/icons/icon-192x192.png": "0b330ab4d9d7c611ba0758cde8be87969a26ec73",
    "/assets/icons/icon-384x384.png": "875c203a8c98c4c16d8a22df3a8f304c6e487ed1",
    "/assets/icons/icon-512x512.png": "1705c7ad8588bbbcb48cd7ecbeaa6d23b63adfbb",
    "/assets/icons/icon-72x72.png": "eb0f0de58b6fccc394c67e234be211e6575e3381",
    "/assets/icons/icon-96x96.png": "84be8cda34892f4853f38a0dafe523f2d5d145ce",
    "/favicon.ico": "416e0016fbf314e9a259894324d5278c525a1bc7",
    "/index.html": "add979d069a5e310c4cc24f37692375e28d27fb7",
    "/main.3dee337d6f3c9b1da05b.js": "a43702c696244009c27f924ad7b1f63529b94b29",
    "/polyfills.2076bdbe1e0f026d7e99.js": "e47b570a294ef2d33186539d04409e1a57392065",
    "/runtime.a5b6306bd520eff5af97.js": "d715afb821094a7513765c85771b942eac35af0f",
    "/styles.1f29ab6809b39ca04b10.css": "da39a3ee5e6b4b0d3255bfef95601890afd80709"
  },
  "navigationUrls": [
    {
      "positive": true,
      "regex": "^\\/.*$"
    },
    {
      "positive": false,
      "regex": "^\\/(?:.+\\/)?[^\\/]*\\.[^\\/]*$"
    },
    {
      "positive": false,
      "regex": "^\\/(?:.+\\/)?[^\\/]*__[^\\/]*$"
    },
    {
      "positive": false,
      "regex": "^\\/(?:.+\\/)?[^\\/]*__[^\\/]*\\/.*$"
    }
  ]
}